quantrs-0.0.1.dist-info/METADATA
quantrs-0.0.1.dist-info/WHEEL
quantrs-0.0.1.dist-info/licenses/LICENSE-APACHE.md
quantrs-0.0.1.dist-info/licenses/LICENSE-MIT.md
quantrs/__init__.py
quantrs/quantrs.cpython-313-x86_64-linux-gnu.so
quantrs-0.0.1.dist-info/RECORD
