Metadata-Version: 2.4
Name: quantrs
Version: 0.0.1
Classifier: Development Status :: 3 - Alpha
Classifier: Intended Audience :: Financial and Insurance Industry
Classifier: License :: OSI Approved :: MIT License
Classifier: License :: OSI Approved :: Apache Software License
Classifier: Programming Language :: Rust
Classifier: Programming Language :: Python :: 3
Classifier: Programming Language :: Python :: 3.8
Classifier: Programming Language :: Python :: 3.9
Classifier: Programming Language :: Python :: 3.10
Classifier: Programming Language :: Python :: 3.11
Classifier: Programming Language :: Python :: 3.12
Classifier: Topic :: Office/Business :: Financial
Classifier: Topic :: Scientific/Engineering :: Mathematics
License-File: LICENSE-APACHE.md
License-File: LICENSE-MIT.md
Summary: Python bindings for a tiny library for quantitative finance (powered by Rust)
Home-Page: https://github.com/carlobortolan/quantrs
Author-email: Carlo Bortolan <carlobortolan@gmail.com>
License: MIT OR Apache-2.0
Requires-Python: >=3.8
Project-URL: Homepage, https://github.com/carlobortolan/quantrs
Project-URL: Repository, https://github.com/carlobortolan/quantrs
Project-URL: Documentation, https://docs.rs/quantrs
